pyinp/__init__.py
pyinp/cli.py
pyinp/dialogs.py
pyinp/utils.py
pyinp/templates/.gitignore
pyinp/templates/.pylintrc
pyinp/templates/LICENSE
pyinp/templates/README.md
pyinp/templates/pylint.yml
pyinp/templates/pyproject.toml
pyinp/templates/python-publish.yml
pyinp-0.1.1.dist-info/licenses/LICENSE
pyinp-0.1.1.dist-info/METADATA
pyinp-0.1.1.dist-info/WHEEL
pyinp-0.1.1.dist-info/entry_points.txt
pyinp-0.1.1.dist-info/top_level.txt
pyinp-0.1.1.dist-info/RECORD
