Metadata-Version: 2.4
Name: pyinp
Version: 0.1.1
Summary: The best and most easy way to create a new python project
Author-email: devs_des1re <arjunbrij8811@gmail.com>
Maintainer-email: devs_des1re <arjunbrij8811@gmail.com>
License: Copyright (c) 2025 devs_des1re
Project-URL: Homepage, https://github.com/devs-des1re/pyinp
Project-URL: Issues, https://github.com/devs-des1re/pyinp/issues
Keywords: app,macOS,windows,linux,flatpak
Classifier: Development Status :: 4 - Beta
Classifier: Intended Audience :: Developers
Classifier: Operating System :: OS Independent
Classifier: Programming Language :: Python :: 3
Classifier: Programming Language :: Python :: 3.10
Classifier: Programming Language :: Python :: 3.11
Classifier: Programming Language :: Python :: 3.12
Classifier: Programming Language :: Python :: 3.13
Classifier: Programming Language :: Python :: 3.14
Classifier: Programming Language :: Python :: 3 :: Only
Classifier: Topic :: Software Development
Classifier: Topic :: Utilities
Requires-Python: >=3.10
License-File: LICENSE
Requires-Dist: pip>=21.2
Requires-Dist: tomli>=2.2
Requires-Dist: typer>=0.16
Dynamic: license-file
